bottle_rest/__init__.py
bottle_rest-0.6.0.dist-info/LICENSE.txt
bottle_rest-0.6.0.dist-info/METADATA
bottle_rest-0.6.0.dist-info/WHEEL
bottle_rest-0.6.0.dist-info/top_level.txt
bottle_rest-0.6.0.dist-info/zip-safe
bottle_rest-0.6.0.dist-info/RECORD
