Metadata-Version: 2.1
Name: bottle-rest
Version: 0.6.0
Summary: Decorators to make REST easier in Bottle.
Home-page: https://github.com/Bystroushaak/rbottle
Author: Bystroushaak
Author-email: bystrousak@kitakitsune.org
License: MIT
Platform: UNKNOWN
Classifier: Framework :: Bottle
Classifier: Topic :: Internet :: WWW/HTTP :: WSGI
Classifier: Topic :: Internet :: WWW/HTTP :: WSGI :: Application
Classifier: Topic :: Software Development :: Libraries
Classifier: Programming Language :: Python :: 3
Classifier: Programming Language :: Python :: 3.6
Classifier: Programming Language :: Python :: 3.8
Classifier: License :: OSI Approved :: MIT License
License-File: LICENSE.txt
Requires-Dist: setuptools
Requires-Dist: bottle
Provides-Extra: docs
Requires-Dist: sphinx ; extra == 'docs'
Requires-Dist: sphinxcontrib-napoleon ; extra == 'docs'
Provides-Extra: test
Requires-Dist: pytest ; extra == 'test'
